{
  "kecamatan": {
    "5108": [
      {"kode":"5108010","nama":"GEROKGAK"},
      {"kode":"5108020","nama":"SERIRIT"},
      {"kode":"5108030","nama":"BUSUNGBIU"},
      {"kode":"5108040","nama":"BANJAR"},
      {"kode":"5108050","nama":"SUKASADA"},
      {"kode":"5108060","nama":"BULELENG"},
      {"kode":"5108070","nama":"SAWAN"},
      {"kode":"5108080","nama":"KUBUTAMBAHAN"},
      {"kode":"5108090","nama":"TEJAKULA"}
    ]
  },
  "kelurahan": {
    "5108010": [
      {"kode":"5108010001","nama":"SUMBERKLAMPOK"},
      {"kode":"5108010002","nama":"PEJARAKAN"},
      {"kode":"5108010003","nama":"SUMBERKIMA"},
      {"kode":"5108010004","nama":"PEMUTERAN"},
      {"kode":"5108010005","nama":"BANYUPOH"},
      {"kode":"5108010006","nama":"PENYABANGAN"},
      {"kode":"5108010007","nama":"MUSI"},
      {"kode":"5108010008","nama":"SANGGALANGIT"},
      {"kode":"5108010009","nama":"GEROKGAK"},
      {"kode":"5108010010","nama":"PATAS"},
      {"kode":"5108010011","nama":"PENGULON"},
      {"kode":"5108010012","nama":"TINGA-TINGA"},
      {"kode":"5108010013","nama":"CELUKANBAWANG"},
      {"kode":"5108010014","nama":"TUKADSUMAGA"}
    ],
    "5108020": [
      {"kode":"5108020001","nama":"UNGGAHAN"},
      {"kode":"5108020002","nama":"GUNUNGSARI"},
      {"kode":"5108020003","nama":"MUNDUK BESTALA"},
      {"kode":"5108020004","nama":"BESTALA"},
      {"kode":"5108020005","nama":"MAYONG"},
      {"kode":"5108020006","nama":"RANGDU"},
      {"kode":"5108020007","nama":"ULARAN"},
      {"kode":"5108020008","nama":"RINGDIKIT"},
      {"kode":"5108020009","nama":"JOANYAR"},
      {"kode":"5108020010","nama":"KALIANGET"},
      {"kode":"5108020011","nama":"TANGGUWISIA"},
      {"kode":"5108020012","nama":"SULANYAH"},
      {"kode":"5108020013","nama":"BUBUNAN"},
      {"kode":"5108020014","nama":"SERIRIT"},
      {"kode":"5108020015","nama":"PENGASTULAN"},
      {"kode":"5108020016","nama":"PATEMON"},
      {"kode":"5108020017","nama":"LOKAPAKSA"},
      {"kode":"5108020018","nama":"UMEANYAR"},
      {"kode":"5108020019","nama":"BANJARASEM"},
      {"kode":"5108020020","nama":"KALISADA"},
      {"kode":"5108020021","nama":"PANGKUNGPARUK"}
    ],
    "5108030": [
      {"kode":"5108030001","nama":"SEPANG KELOD"},
      {"kode":"5108030002","nama":"DAPDAP PUTIH"},
      {"kode":"5108030003","nama":"BONGANCINA"},
      {"kode":"5108030004","nama":"PUCAKSARI"},
      {"kode":"5108030005","nama":"SEPANG"},
      {"kode":"5108030006","nama":"TELAGA"},
      {"kode":"5108030007","nama":"TITAB"},
      {"kode":"5108030008","nama":"KEKERAN"},
      {"kode":"5108030009","nama":"BUSUNGBIU"},
      {"kode":"5108030010","nama":"PELAPUAN"},
      {"kode":"5108030011","nama":"SUBUK"},
      {"kode":"5108030012","nama":"TINGGARSARI"},
      {"kode":"5108030013","nama":"KEDIS"},
      {"kode":"5108030014","nama":"BENGKEL"},
      {"kode":"5108030015","nama":"UMEJERO"}
    ],
    "5108040": [
      {"kode":"5108040001","nama":"BANYUATIS"},
      {"kode":"5108040002","nama":"GESING"},
      {"kode":"5108040003","nama":"MUNDUK"},
      {"kode":"5108040004","nama":"GOBLEG"},
      {"kode":"5108040005","nama":"KAYUPUTIH"},
      {"kode":"5108040006","nama":"TIRTASARI"},
      {"kode":"5108040007","nama":"BANYUSERI"},
      {"kode":"5108040008","nama":"PEDAWA"},
      {"kode":"5108040009","nama":"TIGAWASA"},
      {"kode":"5108040010","nama":"CEMPAGA"},
      {"kode":"5108040011","nama":"SIDETAPA"},
      {"kode":"5108040012","nama":"TAMPEKAN"},
      {"kode":"5108040013","nama":"BANJAR TEGEHA"},
      {"kode":"5108040014","nama":"BANJAR"},
      {"kode":"5108040015","nama":"DENCARIK"},
      {"kode":"5108040016","nama":"TEMUKUS"},
      {"kode":"5108040017","nama":"KALIASEM"}
    ],
    "5108050": [
      {"kode":"5108050001","nama":"PANCASARI"},
      {"kode":"5108050002","nama":"WANAGIRI"},
      {"kode":"5108050003","nama":"AMBENGAN"},
      {"kode":"5108050004","nama":"GITGIT"},
      {"kode":"5108050005","nama":"PEGAYAMAN"},
      {"kode":"5108050006","nama":"SILANGJANA"},
      {"kode":"5108050007","nama":"PEGADUNGAN"},
      {"kode":"5108050008","nama":"PADANGBULIA"},
      {"kode":"5108050009","nama":"SUKASADA"},
      {"kode":"5108050010","nama":"SAMBANGAN"},
      {"kode":"5108050011","nama":"PANJI"},
      {"kode":"5108050012","nama":"PANJI ANOM"},
      {"kode":"5108050013","nama":"TEGALLINGGAH"},
      {"kode":"5108050014","nama":"SELAT"},
      {"kode":"5108050015","nama":"KAYUPUTIH"}
    ],
    "5108060": [
      {"kode":"5108060001","nama":"KALIBUKBUK"},
      {"kode":"5108060002","nama":"ANTURAN"},
      {"kode":"5108060003","nama":"TUKADMUNGGA"},
      {"kode":"5108060004","nama":"PEMARON"},
      {"kode":"5108060005","nama":"BAKTISERAGA"},
      {"kode":"5108060006","nama":"BANYUASRI"},
      {"kode":"5108060007","nama":"BANJAR TEGAL"},
      {"kode":"5108060008","nama":"PAKET AGUNG"},
      {"kode":"5108060009","nama":"BERATAN"},
      {"kode":"5108060010","nama":"LILIGUNDI"},
      {"kode":"5108060011","nama":"KAMPUNG SINGARAJA"},
      {"kode":"5108060012","nama":"KENDRAN"},
      {"kode":"5108060013","nama":"ASTINA"},
      {"kode":"5108060014","nama":"BANJAR JAWA"},
      {"kode":"5108060015","nama":"BANJAR BALI"},
      {"kode":"5108060016","nama":"KAMPUNG KAJANAN"},
      {"kode":"5108060017","nama":"KALIUNTU"},
      {"kode":"5108060018","nama":"KAMPUNG ANYAR"},
      {"kode":"5108060019","nama":"KAMPUNG BUGIS"},
      {"kode":"5108060020","nama":"KAMPUNG BARU"},
      {"kode":"5108060021","nama":"BANYUNING"},
      {"kode":"5108060022","nama":"PENARUKAN"},
      {"kode":"5108060023","nama":"JINENGDALEM"},
      {"kode":"5108060024","nama":"PENGLATAN"},
      {"kode":"5108060025","nama":"PETANDAKAN"},
      {"kode":"5108060026","nama":"SARIMEKAR"},
      {"kode":"5108060027","nama":"NAGASEPAHA"},
      {"kode":"5108060028","nama":"ALASANGKER"},
      {"kode":"5108060029","nama":"POH BERGONG"}
    ],
    "5108070": [
      {"kode":"5108070001","nama":"LEMUKIH"},
      {"kode":"5108070002","nama":"GALUNGAN"},
      {"kode":"5108070003","nama":"SEKUMPUL"},
      {"kode":"5108070004","nama":"BEBETIN"},
      {"kode":"5108070005","nama":"SUDAJI"},
      {"kode":"5108070006","nama":"SAWAN"},
      {"kode":"5108070007","nama":"MENYALI"},
      {"kode":"5108070008","nama":"SUWUG"},
      {"kode":"5108070009","nama":"JAGARAGA"},
      {"kode":"5108070010","nama":"SINABUN"},
      {"kode":"5108070011","nama":"KEROBOKAN"},
      {"kode":"5108070012","nama":"SANGSIT"},
      {"kode":"5108070013","nama":"BUNGKULAN"},
      {"kode":"5108070014","nama":"GIRI EMAS"}
    ],
    "5108080": [
      {"kode":"5108080001","nama":"TAMBAKAN"},
      {"kode":"5108080002","nama":"PAKISAN"},
      {"kode":"5108080003","nama":"BONTIHING"},
      {"kode":"5108080004","nama":"TAJUN"},
      {"kode":"5108080005","nama":"TUNJUNG"},
      {"kode":"5108080006","nama":"DEPEHA"},
      {"kode":"5108080007","nama":"BULIAN"},
      {"kode":"5108080008","nama":"TAMBLANG"},
      {"kode":"5108080009","nama":"BILA"},
      {"kode":"5108080010","nama":"BENGKALA"},
      {"kode":"5108080011","nama":"KUBUTAMBAHAN"},
      {"kode":"5108080012","nama":"BUKTI"},
      {"kode":"5108080013","nama":"MENGENING"}
    ],
    "5108090": [
      {"kode":"5108090001","nama":"SEMBIRAN"},
      {"kode":"5108090002","nama":"PACUNG"},
      {"kode":"5108090003","nama":"JULAH"},
      {"kode":"5108090004","nama":"BONDALEM"},
      {"kode":"5108090005","nama":"MADENAN"},
      {"kode":"5108090006","nama":"TEJAKULA"},
      {"kode":"5108090007","nama":"LES"},
      {"kode":"5108090008","nama":"PENUKTUKAN"},
      {"kode":"5108090009","nama":"SAMBIRENTENG"},
      {"kode":"5108090010","nama":"TEMBOK"}
    ]
  },
  "provinsi": [
    {"kode":"11","nama":"ACEH"},
    {"kode":"12","nama":"SUMATERA UTARA"},
    {"kode":"13","nama":"SUMATERA BARAT"},
    {"kode":"14","nama":"RIAU"},
    {"kode":"15","nama":"JAMBI"},
    {"kode":"16","nama":"SUMATERA SELATAN"},
    {"kode":"17","nama":"BENGKULU"},
    {"kode":"18","nama":"LAMPUNG"},
    {"kode":"19","nama":"KEP. BANGKA BELITUNG"},
    {"kode":"21","nama":"KEP. RIAU"},
    {"kode":"31","nama":"DKI JAKARTA"},
    {"kode":"32","nama":"JAWA BARAT"},
    {"kode":"33","nama":"JAWA TENGAH"},
    {"kode":"34","nama":"DI YOGYAKARTA"},
    {"kode":"35","nama":"JAWA TIMUR"},
    {"kode":"36","nama":"BANTEN"},
    {"kode":"51","nama":"BALI"},
    {"kode":"52","nama":"NUSA TENGGARA BARAT"},
    {"kode":"53","nama":"NUSA TENGGARA TIMUR"},
    {"kode":"61","nama":"KALIMANTAN BARAT"},
    {"kode":"62","nama":"KALIMANTAN TENGAH"},
    {"kode":"63","nama":"KALIMANTAN SELATAN"},
    {"kode":"64","nama":"KALIMANTAN TIMUR"},
    {"kode":"65","nama":"KALIMANTAN UTARA"},
    {"kode":"71","nama":"SULAWESI UTARA"},
    {"kode":"72","nama":"SULAWESI TENGAH"},
    {"kode":"73","nama":"SULAWESI SELATAN"},
    {"kode":"74","nama":"SULAWESI TENGGARA"},
    {"kode":"75","nama":"GORONTALO"},
    {"kode":"76","nama":"SULAWESI BARAT"},
    {"kode":"81","nama":"MALUKU"},
    {"kode":"82","nama":"MALUKU UTARA"},
    {"kode":"91","nama":"PAPUA BARAT"},
    {"kode":"92","nama":"PAPUA"},
    {"kode":"93","nama":"PAPUA SELATAN"},
    {"kode":"94","nama":"PAPUA TENGAH"},
    {"kode":"95","nama":"PAPUA PEGUNUNGAN"},
    {"kode":"96","nama":"PAPUA BARAT DAYA"}
  ]
}
